karrio/mappers/dhl_poland/__init__.py
karrio/mappers/dhl_poland/mapper.py
karrio/mappers/dhl_poland/proxy.py
karrio/mappers/dhl_poland/settings.py
karrio/plugins/dhl_poland/__init__.py
karrio/providers/dhl_poland/__init__.py
karrio/providers/dhl_poland/error.py
karrio/providers/dhl_poland/tracking.py
karrio/providers/dhl_poland/units.py
karrio/providers/dhl_poland/utils.py
karrio/providers/dhl_poland/shipment/__init__.py
karrio/providers/dhl_poland/shipment/cancel.py
karrio/providers/dhl_poland/shipment/create.py
karrio/schemas/dhl_poland/__init__.py
karrio/schemas/dhl_poland/services.py
karrio_dhl_poland-2026.1.4.dist-info/METADATA
karrio_dhl_poland-2026.1.4.dist-info/WHEEL
karrio_dhl_poland-2026.1.4.dist-info/entry_points.txt
karrio_dhl_poland-2026.1.4.dist-info/top_level.txt
karrio_dhl_poland-2026.1.4.dist-info/RECORD
